setup.py
DirkiboysGaussian.egg-info/PKG-INFO
DirkiboysGaussian.egg-info/SOURCES.txt
DirkiboysGaussian.egg-info/dependency_links.txt
DirkiboysGaussian.egg-info/not-zip-safe
DirkiboysGaussian.egg-info/top_level.txt
distributions/Gaussiandistribution.py
distributions/Generaldistribution.py
distributions/__init__.py